linearmodels/__init__.py
linearmodels/_version.py
linearmodels/conftest.py
linearmodels/formula.py
linearmodels/py.typed
linearmodels/__future__/__init__.py
linearmodels/__future__/ordering.py
linearmodels/asset_pricing/__init__.py
linearmodels/asset_pricing/covariance.py
linearmodels/asset_pricing/model.py
linearmodels/asset_pricing/results.py
linearmodels/compat/__init__.py
linearmodels/compat/formulaic.py
linearmodels/compat/pandas.py
linearmodels/compat/statsmodels.py
linearmodels/datasets/__init__.py
linearmodels/datasets/birthweight/__init__.py
linearmodels/datasets/birthweight/birthweight.csv.bz2
linearmodels/datasets/card/__init__.py
linearmodels/datasets/card/card.csv.bz2
linearmodels/datasets/fertility/__init__.py
linearmodels/datasets/fertility/fertility.csv.bz2
linearmodels/datasets/french/__init__.py
linearmodels/datasets/french/french.csv.bz2
linearmodels/datasets/fringe/__init__.py
linearmodels/datasets/fringe/fringe.csv.bz2
linearmodels/datasets/jobtraining/__init__.py
linearmodels/datasets/jobtraining/jobtraining.csv.bz2
linearmodels/datasets/meps/__init__.py
linearmodels/datasets/meps/meps.csv.bz2
linearmodels/datasets/mroz/__init__.py
linearmodels/datasets/mroz/mroz.csv.bz2
linearmodels/datasets/munnell/__init__.py
linearmodels/datasets/munnell/munnell.csv.bz2
linearmodels/datasets/wage/__init__.py
linearmodels/datasets/wage/wage.csv.bz2
linearmodels/datasets/wage_panel/__init__.py
linearmodels/datasets/wage_panel/wage_panel.csv.bz2
linearmodels/iv/__init__.py
linearmodels/iv/_utility.py
linearmodels/iv/absorbing.py
linearmodels/iv/common.py
linearmodels/iv/covariance.py
linearmodels/iv/data.py
linearmodels/iv/gmm.py
linearmodels/iv/model.py
linearmodels/iv/results.py
linearmodels/panel/__init__.py
linearmodels/panel/_utility.c
linearmodels/panel/_utility.cp311-win_amd64.pyd
linearmodels/panel/_utility.pxi
linearmodels/panel/_utility.pyx
linearmodels/panel/covariance.py
linearmodels/panel/data.py
linearmodels/panel/model.py
linearmodels-6.1.dist-info/LICENSE.md
linearmodels-6.1.dist-info/METADATA
linearmodels-6.1.dist-info/WHEEL
linearmodels-6.1.dist-info/top_level.txt
linearmodels-6.1.dist-info/RECORD
