Metadata-Version: 2.1
Name: linearmodels
Version: 6.1
Summary: Linear Panel, Instrumental Variable, Asset Pricing, and System Regression models for Python
Home-page: http://github.com/bashtage/linearmodels
Author: Kevin Sheppard
Author-email: kevin.k.sheppard@gmail.com
License: NCSA
Keywords: linear models,regression,instrumental variables,IV,panel,fixed effects,clustered,heteroskedasticity,endogeneity,instruments,statistics,statistical inference,econometrics
Classifier: Development Status :: 5 - Production/Stable
Classifier: Intended Audience :: End Users/Desktop
Classifier: Intended Audience :: Financial and Insurance Industry
Classifier: Intended Audience :: Science/Research
Classifier: Programming Language :: Python :: 3.9
Classifier: Programming Language :: Python :: 3.10
Classifier: Programming Language :: Python :: 3.11
Classifier: Programming Language :: Python :: 3.12
Classifier: License :: OSI Approved :: University of Illinois/NCSA Open Source License
Classifier: Operating System :: MacOS :: MacOS X
Classifier: Operating System :: Microsoft :: Windows
Classifier: Operating System :: POSIX
Classifier: Programming Language :: Python
Classifier: Topic :: Scientific/Engineering
Requires-Python: >=3.9
License-File: LICENSE.md
Requires-Dist: numpy<3,>=1.22.3
Requires-Dist: pandas>=1.4.0
Requires-Dist: scipy>=1.8.0
Requires-Dist: statsmodels>=0.13.0
Requires-Dist: mypy_extensions>=0.4
Requires-Dist: Cython>=3.0.10
Requires-Dist: pyhdfe>=0.1
Requires-Dist: formulaic>=1.0.0
Requires-Dist: setuptools_scm[toml]<9.0.0,>=8.0.0
